getmetric/__init__.py
getmetric/getmetric.py
getmetric-1.0.2.dist-info/LICENSE
getmetric-1.0.2.dist-info/METADATA
getmetric-1.0.2.dist-info/WHEEL
getmetric-1.0.2.dist-info/top_level.txt
getmetric-1.0.2.dist-info/RECORD
