Metadata-Version: 2.1
Name: getmetric
Version: 1.0.2
Summary: Getmetric python package
Home-page: https://github.com/getmetric/python
Author: Alex Turkovskii
Author-email: darkertb@gmail.com
License: MIT License
Keywords: getmetric package
Platform: UNKNOWN
Classifier: Programming Language :: Python :: 2
Classifier: Programming Language :: Python :: 3
Classifier: License :: OSI Approved :: MIT License
Classifier: Operating System :: OS Independent
